simipro/__init__.py
simipro/simipro.py
simipro-1.1.0.dist-info/METADATA
simipro-1.1.0.dist-info/WHEEL
simipro-1.1.0.dist-info/top_level.txt
simipro-1.1.0.dist-info/RECORD
