Metadata-Version: 2.1
Name: simipro
Version: 1.1.0
Summary: World first popular Chatbot for daily conversation (Service launched in 2002). A unique daily conversation with diversity, fun and vitality. Service provided with 130 million sets of daily small talks in 81 languages compiled through more than 20 million panels. Service in 81 languages. More than 350 million cumulative users worldwide. (Based on June-2018), Records of more than 200 million times of responses made per day.
Home-page: https://github.com/akxvau
Author: akxvau
Author-email: akxvau@gmail.com
License: MIT
Keywords: simsimi,simi,chatBot,chat with simi,simsimi module,simisimi python,simi module,simi py,akxvau,toxinum,simi chatting module,simisimi official,simipro
Classifier: Development Status :: 4 - Beta
Classifier: Intended Audience :: Developers
Classifier: Topic :: Software Development :: Libraries :: Python Modules
Classifier: License :: OSI Approved :: MIT License
Classifier: Programming Language :: Python :: 3
Classifier: Operating System :: OS Independent
Classifier: Environment :: Console
Requires-Python: >=3.9.5
Requires-Dist: requests
